nexla_sdk/__init__.py
nexla_sdk/auth.py
nexla_sdk/client.py
nexla_sdk/exceptions.py
nexla_sdk/http_client.py
nexla_sdk/telemetry.py
nexla_sdk/models/__init__.py
nexla_sdk/models/base.py
nexla_sdk/models/common.py
nexla_sdk/models/enums.py
nexla_sdk/models/access/__init__.py
nexla_sdk/models/access/enums.py
nexla_sdk/models/access/requests.py
nexla_sdk/models/access/responses.py
nexla_sdk/models/credentials/__init__.py
nexla_sdk/models/credentials/enums.py
nexla_sdk/models/credentials/requests.py
nexla_sdk/models/credentials/responses.py
nexla_sdk/models/destinations/__init__.py
nexla_sdk/models/destinations/enums.py
nexla_sdk/models/destinations/requests.py
nexla_sdk/models/destinations/responses.py
nexla_sdk/models/flows/__init__.py
nexla_sdk/models/flows/requests.py
nexla_sdk/models/flows/responses.py
nexla_sdk/models/lookups/__init__.py
nexla_sdk/models/lookups/requests.py
nexla_sdk/models/lookups/responses.py
nexla_sdk/models/metrics/__init__.py
nexla_sdk/models/metrics/enums.py
nexla_sdk/models/metrics/responses.py
nexla_sdk/models/nexsets/__init__.py
nexla_sdk/models/nexsets/enums.py
nexla_sdk/models/nexsets/requests.py
nexla_sdk/models/nexsets/responses.py
nexla_sdk/models/notifications/__init__.py
nexla_sdk/models/notifications/requests.py
nexla_sdk/models/notifications/responses.py
nexla_sdk/models/organizations/__init__.py
nexla_sdk/models/organizations/requests.py
nexla_sdk/models/organizations/responses.py
nexla_sdk/models/projects/__init__.py
nexla_sdk/models/projects/requests.py
nexla_sdk/models/projects/responses.py
nexla_sdk/models/sources/__init__.py
nexla_sdk/models/sources/enums.py
nexla_sdk/models/sources/requests.py
nexla_sdk/models/sources/responses.py
nexla_sdk/models/teams/__init__.py
nexla_sdk/models/teams/requests.py
nexla_sdk/models/teams/responses.py
nexla_sdk/models/users/__init__.py
nexla_sdk/models/users/requests.py
nexla_sdk/models/users/responses.py
nexla_sdk/resources/__init__.py
nexla_sdk/resources/base_resource.py
nexla_sdk-1.0.0.dist-info/METADATA
nexla_sdk-1.0.0.dist-info/WHEEL
nexla_sdk-1.0.0.dist-info/top_level.txt
nexla_sdk-1.0.0.dist-info/RECORD
