Metadata-Version: 2.4
Name: nexla-sdk
Version: 1.0.0
Summary: A Python SDK for the Nexla API
Author-email: Amey Desai <amey.desai@nexla.com>, Saksham Mittal <saksham.mittal@nexla.com>
License: MIT
Project-URL: Homepage, https://github.com/nexla/nexla-sdk
Project-URL: Documentation, https://github.com/nexla/nexla-sdk
Project-URL: Bug Tracker, https://github.com/nexla/nexla-sdk/issues
Classifier: Programming Language :: Python :: 3
Classifier: Programming Language :: Python :: 3.8
Classifier: Programming Language :: Python :: 3.9
Classifier: Programming Language :: Python :: 3.10
Classifier: Programming Language :: Python :: 3.11
Classifier: Programming Language :: Python :: 3.12
Classifier: License :: OSI Approved :: MIT License
Classifier: Operating System :: OS Independent
Requires-Python: >=3.8
Requires-Dist: requests>=2.25.0
Requires-Dist: pydantic>=2.0.0
Provides-Extra: dev
Requires-Dist: pytest>=7.0.0; extra == "dev"
Requires-Dist: pytest-mock>=3.0.0; extra == "dev"
Requires-Dist: python-dotenv>=1.0.0; extra == "dev"
Requires-Dist: pytest-cov>=4.0.0; extra == "dev"
Requires-Dist: pytest-xdist>=3.0.0; extra == "dev"
Requires-Dist: pytest-asyncio>=0.21.0; extra == "dev"
Requires-Dist: hypothesis>=6.0.0; extra == "dev"
Requires-Dist: faker>=18.0.0; extra == "dev"
Requires-Dist: responses>=0.23.0; extra == "dev"
Requires-Dist: freezegun>=1.2.0; extra == "dev"
Requires-Dist: factory-boy>=3.2.0; extra == "dev"
Provides-Extra: tracing
Requires-Dist: opentelemetry-distro; extra == "tracing"
Requires-Dist: opentelemetry-exporter-otlp; extra == "tracing"
